mapaction_logging/__init__.py
mapaction_logging/database.py
mapaction_logging/logger.py
mapaction_logging/main.py
mapaction_logging/status_codes.py
mapaction_logging_module-0.2.6.dist-info/LICENSE.txt
mapaction_logging_module-0.2.6.dist-info/METADATA
mapaction_logging_module-0.2.6.dist-info/WHEEL
mapaction_logging_module-0.2.6.dist-info/entry_points.txt
mapaction_logging_module-0.2.6.dist-info/top_level.txt
mapaction_logging_module-0.2.6.dist-info/RECORD
