Metadata-Version: 2.1
Name: mapaction-logging-module
Version: 0.2.6
Summary: A structured logging module for MapAction applications with a Dashboard
Home-page: https://github.com/mapaction/mapaction_logging_module.git
Author: Harry Sibbenga
Author-email: hsibbenga@mapaction.org
License: UNKNOWN
Platform: UNKNOWN
Classifier: Programming Language :: Python :: 3
Classifier: License :: OSI Approved :: MIT License
Classifier: Operating System :: OS Independent
Requires-Python: >=3.6
License-File: LICENSE.txt
Requires-Dist: streamlit
Requires-Dist: pandas
